LICENSE.txt
MANIFEST.in
README.md
__init__.py
large_list.py
setup.cfg
setup.py
polypoint/__init__.py
polypoint/config.py
polypoint/polypoint.py
polypoint/states.xml
polypoint/utils.pyx
polypoint.egg-info/PKG-INFO
polypoint.egg-info/SOURCES.txt
polypoint.egg-info/dependency_links.txt
polypoint.egg-info/pbr.json
polypoint.egg-info/requires.txt
polypoint.egg-info/top_level.txt