Metadata-Version: 1.1
Name: polypoint
Version: 0.18
Summary: A Python 3 package for classifying geolocation data.
Home-page: https://github.com/josephacall/polypoint
Author: Joseph Call
Author-email: josephacall@gmail.com
License: MIT
Keywords: map determine state for coordinates find point in polygon
Platform: UNKNOWN
Classifier: Development Status :: 4 - Beta
Classifier: Intended Audience :: Developers
Classifier: Topic :: Scientific/Engineering :: Mathematics
Classifier: License :: OSI Approved :: MIT License
Classifier: Programming Language :: Python :: 3.6
